<?xml version="1.0"?>
<!-- Lordys Repository -->
<Repository>
    <DistributedRepositories/>
    <Applications>
        <Application>
            <Name>Oversight</Name>
     <Version>20090707-2BETA</Version>
     <!--
     <DownloadURL>http://oversight.googlecode.com/files/csi_oversight-20090707-2BETA.zip</DownloadURL>
     <DownloadURL>http://www.prodynamic.co.uk/nmt/csirepository/csi_oversight-20090707-2BETA.zip</DownloadURL>
     -->
     <DownloadURL>http://download139.mediafire.com/c1ud0x21g1fg/rzityzyzjfd/csi_oversight-20090707-2BETA.zip</DownloadURL>
            <Author>Lordy</Author>
            <Maintainer>Lordy</Maintainer>
            <Description>Hands free NMT jukebox. See stable release for full description.
If upgrading you should create a new oversight.cfg from oversight.cfg.example. There are new settings for poster view.
If the upgrade doesnt work please use the mini-installer to restore http://prodynamic.co.uk/nmt/installer/index.html
Known Issues: oversight: The index may dissapear during delete operation. A rescan will bring it back.
            </Description>

            <Homepage>http://prodynamic.co.uk/nmt/oversight/oversight.html</Homepage>
     <InstallScript>Apps/AppInit/appinit.cgi?install&amp;oversight-20090707-2BETA.tar</InstallScript>
            <WebInterfaceURL>http://[NMT_IP]:8883/oversight/oversight.cgi</WebInterfaceURL>
            <GayaInterfaceURL>http://localhost:8883/oversight/oversight.cgi</GayaInterfaceURL>
            <Screenshots>
                <URL>http://prodynamic.co.uk/nmt/oversight/ovs2-page1.png</URL>
                <URL>http://prodynamic.co.uk/nmt/oversight/ovs2-textmode.png</URL>
                <URL>http://prodynamic.co.uk/nmt/oversight/ovs2-movie.png</URL>
                <URL>http://prodynamic.co.uk/nmt/oversight/ovs2-tv.png</URL>
                <URL>http://prodynamic.co.uk/nmt/oversight/ovs2-setup.png</URL>
            </Screenshots>
            <UsageInstructions>
                If you used oversight V1, please note the link is changed to http://[NMT_IP]:8883/oversight/oversight.cgi
            </UsageInstructions>
            <Forum>http://www.networkedmediatank.com/showthread.php?tid=17637</Forum>
<Changelog>http://code.google.com/p/oversight/wiki/ChangeLog</Changelog>
        </Application>

        <Application>
            <Name>TvNZB</Name>
     <Version>20090614-2</Version>
     <DownloadURL>http://www.prodynamic.co.uk/nmt/csirepository/csi_tvnzb-20090614-2.zip</DownloadURL>
            <Author>Lordy</Author>
            <Maintainer>Lordy</Maintainer>
            <Description>Automatically download TV oriented NZB files from RSS and feed to nzbget. Also provides NZBget scheduling.</Description>
            <Homepage>http://prodynamic.co.uk/nmt/tvnzb/tvnzb.html</Homepage>
     <InstallScript>Apps/AppInit/appinit.cgi?install&amp;tvnzb-20090614-2.tar</InstallScript>
            <WebInterfaceURL>http://[NMT_IP]:8883/tvnzb.cgi</WebInterfaceURL>
            <GayaInterfaceURL>http://localhost:8883/tvnzb.cgi</GayaInterfaceURL>
            <Screenshots/>
            <UsageInstructions/>
            <Forum>http://www.networkedmediatank.com/showthread.php?tid=11133</Forum>
<Changelog>
    20090614-2: Oops removed some debug lines that broke downloads. 
    20090614-1: Fixed matching agaist titles with html escapes
    20090613-1: Added configurable match limit. Re-Added Skip/Fast Forward
    20090611-1: Bug fix - newzleech feed fixed again.
    20090610-3: Bug fix - feed 0 caused segfault (but left code that stopped newzleech working)
    20090610-1: Accept multiple RSS feeds. More robust nzbget peak scheduling
    20090528-1: Work with nzbget from firmware or from CSI.
</Changelog>
        </Application>

        <Application>
            <Name>Zebedee</Name>
     <Version>20090610-1</Version>
     <DownloadURL>http://www.prodynamic.co.uk/nmt/csirepository/csi_zebedee-20090610-1.zip</DownloadURL>
            <Author>Lordy</Author>
            <Maintainer>Lordy</Maintainer>
            <Description>Another GUI for nzbget that works in the browser or on the TV.</Description>
            <Homepage>http://prodynamic.co.uk/nmt/zebedee/index.html</Homepage>
     <InstallScript>Apps/AppInit/appinit.cgi?install&amp;zebedee-20090610-1.tar</InstallScript>
            <WebInterfaceURL>http://[NMT_IP]:8883/zebedee.cgi</WebInterfaceURL>
            <GayaInterfaceURL>http://localhost:8883/zebedee.cgi</GayaInterfaceURL>
            <WebInterfaceURL/>
            <GayaInterfaceURL/>
            <Screenshots/>
            <UsageInstructions/>
            <Forum>http://www.networkedmediatank.com/forumdisplay.php?fid=64</Forum>
<Changelog>
    20090610-1: Allow NZB upload via URL. Removed test pages as it adds extra maintenance effort and also seemed to confuse some users.
    20090528-1: Work with nzbget from firmware or from CSI.
    TODO : Rewrite for better visibilty of completed, failed jobs.
</Changelog>
        </Application>
    </Applications>
    <Themes/>
    <Indexes/>
    <WaitImageSets/>
    <Webservices/>
</Repository>
